image_features_extract/__init__.py
image_features_extract/image_features_extract.py
image_features_extract/image_features_extract_LITEN.py
image_features_extract-0.4.19.dist-info/LICENSE
image_features_extract-0.4.19.dist-info/METADATA
image_features_extract-0.4.19.dist-info/WHEEL
image_features_extract-0.4.19.dist-info/top_level.txt
image_features_extract-0.4.19.dist-info/RECORD
