Metadata-Version: 2.1
Name: image-features-extract
Version: 0.4.19
Summary: toolbox for extracting features from an image
Home-page: https://github.com/Bertin-fap/image_feature_extract_example
Author: ArrayStream(François Bertin, Amal Chabli)
Author-email: francois.bertin7@wanadoo.fr, amal.chabli@orange.fr
License: MIT
Keywords: Image,data processing
Platform: UNKNOWN
Classifier: Development Status :: 3 - Alpha
Classifier: License :: OSI Approved :: MIT License
Classifier: Programming Language :: Python :: 3.6
Classifier: Topic :: Scientific/Engineering :: Physics
Classifier: Operating System :: OS Independent
Classifier: Intended Audience :: Science/Research
Requires-Dist: pandas
Requires-Dist: numpy
Requires-Dist: scipy
Requires-Dist: PyWavelets
Requires-Dist: scikit-image
